MANIFEST.in
README.rst
bootstrap-buildout.py
buildout.cfg
setup.py
version.txt
xbob/__init__.py
xbob.buildout.egg-info/PKG-INFO
xbob.buildout.egg-info/SOURCES.txt
xbob.buildout.egg-info/dependency_links.txt
xbob.buildout.egg-info/entry_points.txt
xbob.buildout.egg-info/namespace_packages.txt
xbob.buildout.egg-info/not-zip-safe
xbob.buildout.egg-info/requires.txt
xbob.buildout.egg-info/top_level.txt
xbob/buildout/__init__.py
xbob/buildout/develop.py
xbob/buildout/envwrapper.py
xbob/buildout/extension.py
xbob/buildout/gdbpy.py
xbob/buildout/python.py
xbob/buildout/script.py
xbob/buildout/scripts.py
xbob/buildout/test_envwrapper.py
xbob/buildout/tools.py