Metadata-Version: 1.1
Name: xbob.buildout
Version: 1.0.2
Summary: zc.buildout recipes to perform a variety of tasks required by Bob satellite packages
Home-page: http://github.com/bioidiap/bob.buildout
Author: Andre Anjos
Author-email: andre.anjos@idiap.ch
License: GPLv3
Keywords: buildout,sphinx,nose,recipe,eggs,bob
Platform: UNKNOWN
Classifier: Framework :: Bob
Classifier: Development Status :: 4 - Beta
Classifier: Environment :: Plugins
Classifier: Framework :: Buildout :: Recipe
Classifier: Intended Audience :: Developers
Classifier: License :: OSI Approved :: GNU General Public License v3 (GPLv3)
Classifier: Topic :: Software Development :: Build Tools
Classifier: Topic :: Software Development :: Libraries :: Python Modules
Classifier: Natural Language :: English
Classifier: Programming Language :: Python
Classifier: Programming Language :: Python :: 3
